davidkhala/gcp/bq/__init__.py
davidkhala/gcp/bq/migration/__init__.py
davidkhala/gcp/bq/migration/workflow.py
davidkhala/gcp/bq/stream/__init__.py
davidkhala_gcp_bq-0.0.0.dist-info/METADATA
davidkhala_gcp_bq-0.0.0.dist-info/WHEEL
davidkhala_gcp_bq-0.0.0.dist-info/RECORD
